AuthMaster/__init__.py
AuthMaster/auth.py
AuthMaster/models.py
AuthMaster-0.1.dist-info/METADATA
AuthMaster-0.1.dist-info/WHEEL
AuthMaster-0.1.dist-info/top_level.txt
AuthMaster-0.1.dist-info/RECORD
